{
  "image": {
    "name": "jenkins-deploy.fircosoft.net/trust/verify:4.6.3.5-tomcat9.0.37-openjdk11",
    "product": "Trust",
    "asset": "Verify",
    "version": "4.6.3.5",
    "digest": "sha256:e251464b7a24027d467daee527de1c89c7d4cbe00262801aa65607e4f6ef6ca0",
    "buildDate": "2021-11-22T10:46:56.502Z",
    "labels": {
      "com.accuity.asset": "Verify",
      "com.accuity.build-tool": "shadoker",
      "com.accuity.component": "WAR",
      "com.accuity.environment": "release",
      "com.accuity.product": "Trust",
      "com.accuity.product.vcs-branch": "release/4.6.3.x",
      "com.accuity.product.vcs-ref": "ae639f11ffa8f3dec2b5f3d720b5d205b9ac7a2b",
      "com.accuity.product.vcs-url": "ssh://git@dev-bitbucket.fircosoft.net:7999/trustv4/front.git",
      "com.accuity.schema-version": "ALC-1.0.0",
      "com.accuity.version": "4.6.3.5",
      "net.fircosoft.image.category": "Verify",
      "net.fircosoft.image.maintainer": "Sébastien Demanou <sebastien.demanou@accuity.com>",
      "net.fircosoft.image.name": "Firco Trust",
      "net.fircosoft.image.version": "4.6.3.5",
      "org.label-schema.build-date": "2021-05-11T12:21:32Z",
      "org.label-schema.license": "Fircosoft",
      "org.label-schema.name": "Trust Verify WAR 4.6.3.5",
      "org.label-schema.schema-version": "1.0.0-rc.1",
      "org.label-schema.vcs-ref": "44187db52a6702c751ee79ec50670c516d6db060",
      "org.label-schema.vcs-url": "ssh://git@dev-bitbucket.fircosoft.net:7999/fir/shadoker.git",
      "org.label-schema.vendor": "Fircosoft",
      "org.label-schema.version": "4.6.3.5",
      "com.accuity.third-parties.java": "openjdk11",
      "com.accuity.third-parties.web-server": "tomcat9.0.37"
    }
  }
}